gymnasium_hardmaze/__init__.py
gymnasium_hardmaze/data/hardmaze_env.xml
gymnasium_hardmaze/envs/__init__.py
gymnasium_hardmaze/envs/environment.py
gymnasium_hardmaze/envs/fitness_function_factory.py
gymnasium_hardmaze/envs/maze_env.py
gymnasium_hardmaze/envs/components/__init__.py
gymnasium_hardmaze/envs/components/goal.py
gymnasium_hardmaze/envs/components/point_of_interest.py
gymnasium_hardmaze/envs/components/radar.py
gymnasium_hardmaze/envs/components/rangefinder.py
gymnasium_hardmaze/envs/components/robot.py
gymnasium_hardmaze/envs/components/wall.py
gymnasium_hardmaze/envs/rendering/__init__.py
gymnasium_hardmaze/envs/rendering/renderer.py
gymnasium_hardmaze/envs/utils/__init__.py
gymnasium_hardmaze/envs/utils/utils.py
gymnasium_hardmaze/examples/keyboard_agent.py
gymnasium_hardmaze/examples/random_agent.py
gymnasium_hardmaze/tests/test_maze_env.py
gymnasium_hardmaze-0.1.1.dist-info/licenses/LICENSE
gymnasium_hardmaze-0.1.1.dist-info/METADATA
gymnasium_hardmaze-0.1.1.dist-info/WHEEL
gymnasium_hardmaze-0.1.1.dist-info/top_level.txt
gymnasium_hardmaze-0.1.1.dist-info/RECORD
