Metadata-Version: 2.4
Name: gymnasium-hardmaze
Version: 0.1.1
Summary: A Gymnasium-compatible implementation of hardmaze environment
Author-email: Stefano Palmieri <teaspoonaistu@gmail.com>
License-Expression: MIT
Project-URL: Homepage, https://github.com/Teaspoon-AI/gymnasium-hardmaze
Project-URL: Bug Tracker, https://github.com/Teaspoon-AI/gymnasium-hardmaze/issue
Classifier: Programming Language :: Python :: 3
Classifier: Programming Language :: Python :: 3.8
Classifier: Programming Language :: Python :: 3.9
Classifier: Programming Language :: Python :: 3.10
Classifier: Programming Language :: Python :: 3.11
Classifier: Programming Language :: Python :: 3.12
Classifier: Operating System :: OS Independent
Classifier: Topic :: Scientific/Engineering :: Artificial Intelligence
Requires-Python: >=3.8
License-File: LICENSE
Requires-Dist: gymnasium>=1.1.1
Requires-Dist: pygame<3.0,>=2.5
Requires-Dist: numpy>=1.21.0
Requires-Dist: beautifulsoup4>=4.6.0
Requires-Dist: lxml>=4.6.3
Requires-Dist: setuptools>=75.3.2
Dynamic: license-file
